PythonTestingTutorial/README.md
PythonTestingTutorial/__init__.py
PythonTestingTutorial/__main__.py
PythonTestingTutorial/file.epub
PythonTestingTutorial/index.html
PythonTestingTutorial/css/__init__.py
PythonTestingTutorial/css/annotations.css
PythonTestingTutorial/css/main.css
PythonTestingTutorial/css/normalize.css
PythonTestingTutorial/css/popup.css
PythonTestingTutorial/font/__init__.py
PythonTestingTutorial/font/fontello.eot
PythonTestingTutorial/font/fontello.svg
PythonTestingTutorial/font/fontello.ttf
PythonTestingTutorial/font/fontello.woff
PythonTestingTutorial/img/__init__.py
PythonTestingTutorial/img/annotator-glyph-sprite.png
PythonTestingTutorial/img/annotator-icon-sprite.png
PythonTestingTutorial/img/apple-touch-icon.png
PythonTestingTutorial/img/cancelfullscreen.png
PythonTestingTutorial/img/close.png
PythonTestingTutorial/img/fullscreen.png
PythonTestingTutorial/img/loader.gif
PythonTestingTutorial/img/menu-icon.png
PythonTestingTutorial/img/save.png
PythonTestingTutorial/img/saved.png
PythonTestingTutorial/img/settings-s.png
PythonTestingTutorial/img/settings.png
PythonTestingTutorial/img/star.png
PythonTestingTutorial/js/__init__.py
PythonTestingTutorial/js/epub.js
PythonTestingTutorial/js/epub.min.js
PythonTestingTutorial/js/epub.min.map
PythonTestingTutorial/js/hooks.min.js
PythonTestingTutorial/js/hooks.min.map
PythonTestingTutorial/js/reader.js
PythonTestingTutorial/js/reader.js.map
PythonTestingTutorial/js/reader.min.js
PythonTestingTutorial/js/reader.min.map
PythonTestingTutorial/js/hooks/__init__.py
PythonTestingTutorial/js/hooks/extensions/__init__.py
PythonTestingTutorial/js/hooks/extensions/highlight.js
PythonTestingTutorial/js/libs/__init__.py
PythonTestingTutorial/js/libs/jquery.min.js
PythonTestingTutorial/js/libs/localforage.min.js
PythonTestingTutorial/js/libs/screenfull.js
PythonTestingTutorial/js/libs/screenfull.min.js
PythonTestingTutorial/js/libs/zip.min.js
PythonTestingTutorial/js/plugins/__init__.py
python_testing_tutorial-2024.3.4.0.dist-info/METADATA
python_testing_tutorial-2024.3.4.0.dist-info/WHEEL
python_testing_tutorial-2024.3.4.0.dist-info/entry_points.txt
python_testing_tutorial-2024.3.4.0.dist-info/top_level.txt
python_testing_tutorial-2024.3.4.0.dist-info/RECORD
